gushwork_logger/__init__.py
gushwork_logger/logger.py
gushwork_logger-0.1.0.dist-info/licenses/LICENSE
tests/__init__.py
tests/test_logger.py
gushwork_logger-0.1.0.dist-info/METADATA
gushwork_logger-0.1.0.dist-info/WHEEL
gushwork_logger-0.1.0.dist-info/top_level.txt
gushwork_logger-0.1.0.dist-info/RECORD
